nuart/__init__.py
nuart/biclustering/__init__.py
nuart/biclustering/bartmap.py
nuart/clustering/__init__.py
nuart/clustering/dual_vigilance_art.py
nuart/clustering/dual_vigilance_fuzzy_art.py
nuart/clustering/dual_vigilance_hypersphere_art.py
nuart/clustering/fuzzy_art.py
nuart/clustering/hypersphere_art.py
nuart/common/__init__.py
nuart/common/linear_algebra.py
nuart/common/utils.py
nuart/preprocessing/__init__.py
nuart/preprocessing/vat.py
nuart-0.0.5.dist-info/LICENSE
nuart-0.0.5.dist-info/METADATA
nuart-0.0.5.dist-info/WHEEL
nuart-0.0.5.dist-info/top_level.txt
nuart-0.0.5.dist-info/RECORD
