Metadata-Version: 2.1
Name: nuart
Version: 0.0.5
Summary: NuART-Py: Python Library of Adaptive Resonance Theory Neural Networks
Home-page: https://github.com/ACIL-Group/NuART-Py
Author: Islam Elnabarawy
Author-email: islam.ossama@gmail.com
License: UNKNOWN
Platform: UNKNOWN
Classifier: Programming Language :: Python :: 3
Classifier: License :: OSI Approved :: Apache Software License
Classifier: Operating System :: OS Independent
Requires-Dist: numpy
Requires-Dist: scikit-learn
Requires-Dist: scipy
